{"mesas":{
  "Grande":["1","2","3","4","5","6"],
  "Sillon":["1","2","3","4","5","6"],
  "Balcon":["1","2","3","4","5","6"],
  "Adentro":["1","2","3","4","5"],
  "Esq":["1","2","3","4","5","6","7","8","9","10"],
  "Patio":["1","1b","2","2b","3","3b","4","4b","5","5b","6","6b","7","7b","8","9","10"],
  "Banco":["1", "2", "3"]
},
"datos":[
  ["trago speed Lt", "10200"],
  ["Absolut speed", "6000"],
  ["Adicional", "1500"],
  ["Agua", "2300"],
  ["Alitas", "6500"],
  ["APA", "4000"],
  ["APA H H", "3000"],
  ["APA Litro", "7800"],
  ["APA Litro H H", "6000"],
  ["Aros cebolla", "7000"],
  ["Bajon birrero", "7500"],
  ["Bastones Muzza", "8200"],
  ["Bondiola", "12500"],
  ["Boiler maker", "6500"],
  ["Boulevardier", "4500"],
  ["Funghi", "6000"],
  ["Campari", "4600"],
  ["Campari H H", "3300"],
  ["Campari Litro", "9000"],
  ["Campari Litro H H", "6500"],
  ["Caipiriña", "5500"],
  ["Benjamin tinto", "7500"],
  ["Caipiroska", "5500"],
  ["Gin daisy L H H", "8000"],
  ["Chop Gaseosa", "2300"],
  ["Churrasquito", "12500"],
  ["Cinzano", "4600"],
  ["Chopp jugo", "2800"],
  ["Cinzano Litro", "9000"],
  ["Empanada", "1500"],
  ["Cosecha", "7500"],
  ["Cosecha speed", "12500"],
  ["Doble ipa HH", "3500"],
  ["Envase Pet", "1000"],
  ["Doble ipa", "4500"],
  ["Espumante", "7500"],
  ["Estacional", "3800"],
  ["Estacional H H", "2800"],
  ["Estacional Litro", "7500"],
  ["Estacional Litro H H", "5500"],
  ["Fernet", "4600"],
  ["Fernet H H", "3300"],
  ["Fernet Litro", "9000"],
  ["Fernet Litro H H", "6500"],
  ["Gancia", "4600"],
  ["Gancia H H", "3300"],
  ["Gancia L ", "9000"],
  ["Gancia L H H", "6500"],
  ["Doble ipa L", "8800"],
  ["Gancia batido", "5200"],
  ["Gancia americanino", "5200"],
  ["Gancia batido L", "10000"],
  ["Gancia americanino L", "10000"],
  ["Emilia tinto", "10000"],
  ["Envase vaso", "500"],
  ["Gin", "4600"],
  ["Gin H H", "3300"],
  ["Gin Litro", "9000"],
  ["Gin Litro H H", "6500"],
  ["Gin daisy", "5200"],
  ["Absolut litro", "12000"],
  ["Gin daisy L", "10000"],
  ["Doble ipa L HH", "7000"],
  ["Golden", "3800"],
  ["Golden H H", "2800"],
  ["Golden Litro", "7500"],
  ["Golden Litro H H", "5500"],
  ["Funghi grande", "11000"],
  ["Caprese Grande", "10000"],
  ["Hamb simple", "9000"],
  ["Hamb doble", "10200"],
  ["Hamb Triple", "11500"],
  ["Honey", "3800"],
  ["Honey H H", "2800"],
  ["Honey Litro", "7500"],
  ["Honey Litro H H", "5500"],
  ["Invitada", "3800"],
  ["invitada HH", "2800"],
  ["Invitada Litro", "7500"],
  ["Invitada Litro HH", "5500"],
  ["IPA", "4000"],
  ["IPA H H", "3000"],
  ["IPA Litro", "7800"],
  ["IPA Litro H H", "6000"],
  ["J y M", "5400"],
  ["J y M Grande", "10000"],
  ["Jagger speed", "7000"],
  ["Jagger tonic", "7000"],
  ["caipiroska HH", "4000"],
  ["Jagger litro", "13600"],
  ["Jagger shot", "5000"],
  ["Jim Bean"],
  ["Jonnie Walker Negro", "8500"],
  ["Jonnie Walker Rojo", "6500"],
  ["caipiriña HH", "4000"],
  ["Laguna azul", "5000"],
  ["Laguna azul HH", "4000"],
  ["Laguna azul L", "9800"],
  ["Laguna azul L Hh", "8000"],
  ["Levite/H2O", "2300"],
  ["Mila sola", "11500"],
  ["mila napo", "12500"],
  ["Mila huelga", "12500"],
  ["Muzza", "5000"],
  ["Muzza Grande", "9200"],
  ["Mockingbird", "5500"],
  ["Mojito", "5500"],
  ["Mojito HH", "4000"],
  ["Napo", "5400"],
  ["Napo Grande", "10000"],
  ["Negroni", "5500"],
  ["Panq dulce", "5200"],
  ["Panq manzana", "5200"],
  ["whiscola litro", "9000"],
  ["Pago"],
  ["Pancho", "6500"],
  ["Papas solas", "5800"],
  ["Salchipapa", "7500"],
  ["Papas ad", "6800"],
  ["Papas huelga", "7800"],
  ["Picada", "19500"],
  ["Pizza huelga", "12500"],
  ["Pollo Crispy", "8500"],
  ["Piel de iguana", "5000"],
  ["Piel de iguana HH", "4000"],
  ["Piel de iguana L", "9800"],
  ["Piel de iguana L HH", "8000"],
  ["Porter", "3800"],
  ["Porter H H", "2800"],
  ["Porter Litro", "7500"],
  ["Porter Litro H H", "5500"],
  ["gancia batido HH", "4000"],
  ["gancia batido L HH", "8000"],
  ["Promo Apa", "4000"],
  ["Provo ind", "5400"],
  ["Provoleta Grande", "10000"],
  ["Provoleta", "7500"],
  ["Rabas", "12000"],
  ["Ravioles", "7000"],
  ["Caprese", "5400"],
  ["Ron", "5000"],
  ["Ron HH", "4000"],
  ["Ron Litro", "9800"],
  ["Ron HH L", "8000"],
  ["Roquefort", "5400"],
  ["Roquefort grande", "10000"],
  ["Rucula", "5400"],
  ["Rucula Grande", "10000"],
  ["Scotish", "3800"],
  ["Scotish H H", "2800"],
  ["Scotish Litro", "7500"],
  ["Scotish Litro H H", "5500"],
  ["shot tequila", "3000"],
  ["shot absolut", "4500"],
  ["Shot vodka", "3000"],
  ["Speed", "2800"],
  ["Super Papas", "8800"],
  ["Submarino", "6500"],
  ["Tarjeta"],
  ["Tequila sunrise", "5200"],
  ["Tequila sunrise HH", "4000"],
  ["Tequila sunrise L", "10000"],
  ["whiscola H H L", "6500"],
  ["Trago Huelga", "5200"],
  ["Trago Huelga Litro", "10000"],
  ["Trago speed", "5300"],
  ["Vodka", "4600"],
  ["Vodka H H", "3300"],
  ["Vodka Litro", "9000"],
  ["Vodka Litro H H", "6500"],
  ["whiscola", "4600"],
  ["whiscola H H", "3300"],
  ["Whiskey speed", "5300"],
  ["Whiskey speed L", "10200"],
  ["Cuatro quesos", "5400"],
  ["Cuatro quesos grande", "10000"],
  ["Tostado", "8000"],
  ["Tostado ruc", "9800"],
  ["Caprese grande", "10000"]
]

}